yabt/__init__.py
yabt/yabt.py
yet_another_backup_tool-0.1.dist-info/LICENSE
yet_another_backup_tool-0.1.dist-info/METADATA
yet_another_backup_tool-0.1.dist-info/WHEEL
yet_another_backup_tool-0.1.dist-info/entry_points.txt
yet_another_backup_tool-0.1.dist-info/top_level.txt
yet_another_backup_tool-0.1.dist-info/RECORD
