Metadata-Version: 2.2
Name: yet-another-backup-tool
Version: 0.1
Classifier: Programming Language :: Python :: 3
Classifier: License :: OSI Approved :: MIT License
Classifier: Operating System :: OS Independent
License-File: LICENSE
Requires-Dist: pyaml
Requires-Dist: argparse
Dynamic: classifier
Dynamic: requires-dist
